jupyter_functions/__init__.py
jupyter_functions/__main__.py
jupyter_functions/_version.py
jupyter_functions/application.py
jupyter_functions/serverapplication.py
jupyter_functions/handlers/__init__.py
jupyter_functions/handlers/base.py
jupyter_functions/handlers/config/__init__.py
jupyter_functions/handlers/config/handler.py
jupyter_functions/handlers/echo/__init__.py
jupyter_functions/handlers/echo/handler.py
jupyter_functions/handlers/index/__init__.py
jupyter_functions/handlers/index/handler.py
jupyter_functions/handlers/ping/__init__.py
jupyter_functions/handlers/ping/handler.py
jupyter_functions/handlers/proxy/__init__.py
jupyter_functions/handlers/proxy/handler.py
jupyter_functions/handlers/relay/__init__.py
jupyter_functions/handlers/relay/handler.py
jupyter_functions/static/README.md
jupyter_functions/static/main.jupyter-functions.js
jupyter_functions/templates/index.html
jupyter_functions/tests/__init__.py
jupyter_functions/tests/test_handlers.py
jupyter_functions-0.0.1.data/data/etc/jupyter/jupyter_notebook_config.d/jupyter_functions.json
jupyter_functions-0.0.1.data/data/etc/jupyter/jupyter_server_config.d/jupyter_functions.json
jupyter_functions-0.0.1.data/data/share/jupyter/labextensions/@datalayer/jupyter-functions/build_log.json
jupyter_functions-0.0.1.data/data/share/jupyter/labextensions/@datalayer/jupyter-functions/package.json
jupyter_functions-0.0.1.data/data/share/jupyter/labextensions/@datalayer/jupyter-functions/schemas/@datalayer/jupyter-functions/package.json.orig
jupyter_functions-0.0.1.data/data/share/jupyter/labextensions/@datalayer/jupyter-functions/schemas/@datalayer/jupyter-functions/plugin.json
jupyter_functions-0.0.1.data/data/share/jupyter/labextensions/@datalayer/jupyter-functions/static/lib_index_js-webpack_sharing_consume_default_lumino_coreutils-webpack_sharing_consume_default-ca7f34.414f680a8c64a441cc74.js
jupyter_functions-0.0.1.dist-info/METADATA
jupyter_functions-0.0.1.dist-info/WHEEL
jupyter_functions-0.0.1.dist-info/entry_points.txt
jupyter_functions-0.0.1.dist-info/licenses/LICENSE
jupyter_functions-0.0.1.dist-info/RECORD
